{
  "main": [
    {
      "name": "Inicio",
      "url": "/"
    },
    {
      "name": "Partidos",
      "url": "/partidos"
    },
    {
      "name": "Posiciones",
      "url": "/posiciones"
    },
    {
      "name": "Galeria",
      "url": "/blog"
    },
    {
      "name": "Nosotros",
      "url": "/elements"
    }
  ],
  "footer": [
    {
      "name": "FC Albatros",
      "menu": [
        {
          "text": "Posiciones",
          "url": "/posiciones"
        },
        {
          "text": "Ir al inicio",
          "url": "#"
        }
      ]
    }
  ]
}
